zamp_temporalio-1.11.2.dist-info/METADATA
zamp_temporalio-1.11.2.dist-info/WHEEL
zamp_temporalio-1.11.2.dist-info/licenses/LICENSE
zamp_temporalio/service.py
zamp_temporalio/bridge/worker.py
zamp_temporalio/bridge/Cargo.toml
zamp_temporalio/bridge/proto/core_interface_pb2.py
zamp_temporalio/bridge/proto/bridge/bridge_pb2.pyi
zamp_temporalio/bridge/proto/bridge/__init__.py
zamp_temporalio/bridge/proto/bridge/bridge_pb2.py
zamp_temporalio/bridge/proto/health/v1/health_pb2.py
zamp_temporalio/bridge/proto/health/v1/__init__.py
zamp_temporalio/bridge/proto/health/v1/health_pb2.pyi
zamp_temporalio/bridge/proto/health/__init__.py
zamp_temporalio/bridge/proto/__init__.py
zamp_temporalio/bridge/proto/child_workflow/__init__.py
zamp_temporalio/bridge/proto/child_workflow/child_workflow_pb2.pyi
zamp_temporalio/bridge/proto/child_workflow/child_workflow_pb2.py
zamp_temporalio/bridge/proto/core_interface_pb2.pyi
zamp_temporalio/bridge/proto/activity_result/activity_result_pb2.py
zamp_temporalio/bridge/proto/activity_result/__init__.py
zamp_temporalio/bridge/proto/activity_result/activity_result_pb2.pyi
zamp_temporalio/bridge/proto/common/common_pb2.pyi
zamp_temporalio/bridge/proto/common/common_pb2.py
zamp_temporalio/bridge/proto/common/__init__.py
zamp_temporalio/bridge/proto/nexus/nexus_pb2.pyi
zamp_temporalio/bridge/proto/nexus/__init__.py
zamp_temporalio/bridge/proto/nexus/nexus_pb2.py
zamp_temporalio/bridge/proto/core_interface_pb2_grpc.pyi
zamp_temporalio/bridge/proto/workflow_commands/workflow_commands_pb2.pyi
zamp_temporalio/bridge/proto/workflow_commands/__init__.py
zamp_temporalio/bridge/proto/workflow_commands/workflow_commands_pb2.py
zamp_temporalio/bridge/proto/activity_task/__init__.py
zamp_temporalio/bridge/proto/activity_task/activity_task_pb2.pyi
zamp_temporalio/bridge/proto/activity_task/activity_task_pb2.py
zamp_temporalio/bridge/proto/core_interface_pb2_grpc.py
zamp_temporalio/bridge/proto/workflow_activation/__init__.py
zamp_temporalio/bridge/proto/workflow_activation/workflow_activation_pb2.py
zamp_temporalio/bridge/proto/workflow_activation/workflow_activation_pb2.pyi
zamp_temporalio-1.11.2.dist-info/RECORD
